pyscanasdk/__init__.py
pyscanasdk/moderation.py
pyscanasdk/v3.py
pyscanasdk-1.0.9.dist-info/METADATA
pyscanasdk-1.0.9.dist-info/WHEEL
pyscanasdk-1.0.9.dist-info/top_level.txt
pyscanasdk-1.0.9.dist-info/RECORD
